codecontest/__init__.py
codecontest/ccclean.py
codecontest/cfparser.py
codecontest/cppast.py
codecontest/cppcompare.py
codecontest/cppinline.py
codecontest/cpprun.py
codecontest/pyinstall.py
codecontest/codeforces/pybind11.cpp
codecontest-1.1.0.dist-info/METADATA
codecontest-1.1.0.dist-info/WHEEL
codecontest-1.1.0.dist-info/entry_points.txt
codecontest-1.1.0.dist-info/top_level.txt
codecontest-1.1.0.dist-info/RECORD
