Metadata-Version: 2.1
Name: codecontest
Version: 1.1.0
Author-email: dy <jealousing@alumni.sjtu.edu.cn>
Requires-Python: >=3.7
Requires-Dist: numpy
Requires-Dist: pybind11
Requires-Dist: pandas
Requires-Dist: bs4
Provides-Extra: dev
Requires-Dist: pytest ; extra == 'dev'
Requires-Dist: pip-tools ; extra == 'dev'
Requires-Dist: pybind11 ; extra == 'dev'
Requires-Dist: build ; extra == 'dev'
Requires-Dist: twine ; extra == 'dev'
